screen_recorder_sdk/__init__.py
screen_recorder_sdk/exit_codes.py
screen_recorder_sdk/screen_recorder.py
screen_recorder_sdk/lib/ScreenRecorder.dll
screen_recorder_sdk-1.3.0.dist-info/METADATA
screen_recorder_sdk-1.3.0.dist-info/WHEEL
screen_recorder_sdk-1.3.0.dist-info/top_level.txt
screen_recorder_sdk-1.3.0.dist-info/zip-safe
screen_recorder_sdk-1.3.0.dist-info/RECORD
