Metadata-Version: 2.1
Name: screen-recorder-sdk
Version: 1.3.0
Summary: Library to take screenshots and record video from desktop
Home-page: https://github.com/Andrey1994/screen_recorder_sdk
Author: Andrey Parfenov
Author-email: a1994ndrey@gmail.com
License: UNKNOWN
Platform: UNKNOWN
Classifier: Development Status :: 2 - Pre-Alpha
Classifier: Topic :: Utilities
Requires-Python: >=3
Requires-Dist: numpy
Requires-Dist: Pillow
